{
  "ClaimCopyrightCreatePost": {
    "Required": [
      "copyrightMediaId",
      "copyrightMediaModule",
      "copyrightRole",
      "copyrightFirstname",
      "copyrightLastname",
      "copyrightStreet",
      "copyrightCity",
      "copyrightPostalCode",
      "copyrightCountry",
      "copyrightUsername",
      "copyrightEmail",
      "copyrightTelephone",
      "copyrightTerms"
    ],
    "Unrequired": [
      "copyrightInfringedWork",
      "copyrightCompany",
      "copyrightRightsHolder",
      "copyrightCategory",
      "copyrightCategoryOther"
    ]
  },
  "ClaimCopyrightIdGet": {
    "Required": [
      "id"
    ],
    "Unrequired": []
  },
  "ClaimProfileCreatePost": {
    "Required": [
      "profileName",
      "claimType",
      "identityFileUrl1",
      "identityFileUrl2"
    ],
    "Unrequired": []
  },
  "ClaimProfileIdGet": {
    "Required": [
      "id"
    ],
    "Unrequired": []
  },
  "DdexDdexIngestPost": {
    "Required": [
      "ddexDirectoryPath"
    ],
    "Unrequired": []
  },
  "DdexCwrIngestPost": {
    "Required": [
      "cwrDirectoryPath"
    ],
    "Unrequired": []
  },
  "InsidetracksCreatePost": {
    "Required": [
      "blogTitle",
      "blogCategory",
      "blogPublishDate",
      "blogContent"
    ],
    "Unrequired": [
      "audioImage"
    ]
  },
  "InsidetracksIdDelete": {
    "Required": [
      "id"
    ],
    "Unrequired": []
  },
  "InsidetracksIdGet": {
    "Required": [
      "id"
    ],
    "Unrequired": []
  },
  "InsidetracksIdPut": {
    "Required": [
      "id"
    ],
    "Unrequired": [
      "blogTitle",
      "blogCategory",
      "blogPublishDate",
      "blogContent",
      "audioImage"
    ]
  },
  "InsidetracksListGet": {
    "Required": [],
    "Unrequired": [
      "limit",
      "title",
      "category",
      "artist"
    ]
  },
  "LicenseCreatePost": {
    "Required": [
      "licenseMediaType",
      "licenseMediaId",
      "licenseStartDate",
      "licenseEndDate",
      "licenseTerritories",
      "licenseUseType",
      "licenseLicenseeType",
      "licenseLicenseeName",
      "licenseAdvanceFee",
      "licensePerDownloadPrice"
    ],
    "Unrequired": [
      "licenseRoyalty",
      "licenseAdvanceRecoupable",
      "licenseLimitDistribution",
      "licenseEarliestSalesDistributionDate",
      "licenseLatestSalesDistributionDate"
    ]
  },
  "LicenseIdDelete": {
    "Required": [
      "id"
    ],
    "Unrequired": []
  },
  "LicenseIdGet": {
    "Required": [
      "id"
    ],
    "Unrequired": []
  },
  "LicenseIdPut": {
    "Required": [
      "id",
      "licenseStartDate",
      "licenseEndDate",
      "licenseTerritories",
      "licenseUseType",
      "licenseLicenseeType",
      "licenseLicenseeName",
      "licenseAdvanceFee",
      "licensePerDownloadPrice"
    ],
    "Unrequired": [
      "licenseRoyalty",
      "licenseAdvanceRecoupable",
      "licenseLimitDistribution",
      "licenseEarliestSalesDistributionDate",
      "licenseLatestSalesDistributionDate"
    ]
  },
  "MixesCreatePost": {
    "Required": [
      "audioTitle",
      "audioGenre",
      "audioReleaseDate",
      "audioText",
      "audioImage"
    ],
    "Unrequired": [
      "audioMixVersion",
      "audioLabel",
      "audioArtist",
      "audioAdditionalArtists",
      "audioIsrc",
      "audioCatalog",
      "audioKobalt"
    ]
  },
  "MixesIdDelete": {
    "Required": [
      "id"
    ],
    "Unrequired": []
  },
  "MixesIdGet": {
    "Required": [
      "id"
    ],
    "Unrequired": []
  },
  "MixesIdPut": {
    "Required": [
      "id"
    ],
    "Unrequired": [
      "audioTitle",
      "audioGenre",
      "audioReleaseDate",
      "audioText",
      "audioImage",
      "audioMixVersion",
      "audioLabel",
      "audioArtist",
      "audioAdditionalArtists",
      "audioIsrc",
      "audioCatalog",
      "audioKobalt"
    ]
  },
  "MixesListGet": {
    "Required": [],
    "Unrequired": [
      "limit",
      "title",
      "genre",
      "artist",
      "dateRangeFrom",
      "dateRangeTo"
    ]
  },
  "PlaylistsCreatePost": {
    "Required": [
      "name",
      "type",
      "image"
    ],
    "Unrequired": [
      "genre",
      "description"
    ]
  },
  "PlaylistsIdDelete": {
    "Required": [
      "id"
    ],
    "Unrequired": []
  },
  "PlaylistsIdGet": {
    "Required": [
      "id"
    ],
    "Unrequired": []
  },
  "PlaylistsIdPut": {
    "Required": [
      "id",
      "name",
      "type",
      "image"
    ],
    "Unrequired": [
      "genre",
      "description"
    ]
  },
  "PlaylistsItemsAddPost": {
    "Required": [
      "playlistId",
      "mediaId",
      "mediaType"
    ],
    "Unrequired": []
  },
  "PlaylistsItemsDeleteIdDelete": {
    "Required": [
      "id",
      "itemId"
    ],
    "Unrequired": []
  },
  "PlaylistsItemsIdGet": {
    "Required": [
      "id"
    ],
    "Unrequired": []
  },
  "PlaylistsListGet": {
    "Required": [],
    "Unrequired": [
      "limit",
      "name",
      "genre",
      "artist"
    ]
  },
  "ProfileListGet": {
    "Required": [],
    "Unrequired": [
      "limit",
      "name",
      "type",
      "country",
      "city"
    ]
  },
  "ReleaseCreatePost": {
    "Required": [
      "releaseMediaType",
      "releaseMediaId",
      "releaseStartDate",
      "releaseEndDate",
      "releaseTerritories",
      "releasePrice"
    ],
    "Unrequired": [
      "releaseAllowdownloads",
      "releaseShowads",
      "releaseSubscriberonly",
      "releaseSocialShare",
      "releaseSampleTimeStart",
      "releaseSampleTimeEnd",
      "releaseEmbedplayer",
      "releaseDomainWhitelisting",
      "releaseLicenseeType",
      "releaseLicenseeName"
    ]
  },
  "ReleaseIdDelete": {
    "Required": [
      "id"
    ],
    "Unrequired": []
  },
  "ReleaseIdGet": {
    "Required": [
      "id"
    ],
    "Unrequired": []
  },
  "ReleaseIdPut": {
    "Required": [
      "id",
      "releasePrice"
    ],
    "Unrequired": [
      "releaseStartDate",
      "releaseEndDate",
      "releaseTerritories",
      "releaseAllowdownloads",
      "releaseShowads",
      "releaseSubscriberonly",
      "releaseSocialShare",
      "releaseSampleTimeStart",
      "releaseSampleTimeEnd",
      "releaseEmbedplayer",
      "releaseDomainWhitelisting"
    ]
  },
  "SongsCreatePost": {
    "Required": [
      "audioTitle",
      "audioGenre",
      "audioReleaseDate",
      "audioText",
      "audioImage",
      "audioKey"
    ],
    "Unrequired": [
      "audioMixVersion",
      "audioAlbum",
      "audioLabel",
      "audioArtist",
      "audioRemixer",
      "audioLyrics",
      "audioBpm",
      "audioIswc",
      "audioIsrc",
      "audioCatalog",
      "audioKobalt",
      "audioUpc"
    ]
  },
  "SongsIdDelete": {
    "Required": [
      "id"
    ],
    "Unrequired": []
  },
  "SongsIdGet": {
    "Required": [
      "id"
    ],
    "Unrequired": []
  },
  "SongsIdPut": {
    "Required": [
      "id"
    ],
    "Unrequired": [
      "audioTitle",
      "audioGenre",
      "audioReleaseDate",
      "audioText",
      "audioImage",
      "audioKey",
      "audioMixVersion",
      "audioAlbum",
      "audioLabel",
      "audioArtist",
      "audioRemixer",
      "audioLyrics",
      "audioBpm",
      "audioIswc",
      "audioIsrc",
      "audioCatalog",
      "audioKobalt",
      "audioUpc"
    ]
  },
  "SongsListGet": {
    "Required": [],
    "Unrequired": [
      "limit",
      "title",
      "genre",
      "artist",
      "dateRangeFrom",
      "dateRangeTo"
    ]
  },
  "SplitsCreatePost": {
    "Required": [
      "splitType",
      "splitMod",
      "splitItemId",
      "splitUserFile"
    ],
    "Unrequired": []
  },
  "StemsCreatePost": {
    "Required": [
      "audioTitle",
      "audioKey",
      "audioType",
      "audioReleaseDate",
      "audioText",
      "audioImage"
    ],
    "Unrequired": [
      "audioMixVersion",
      "audioSongId",
      "audioLabel",
      "audioArtist",
      "audioRemixer",
      "audioLyrics",
      "audioBpm",
      "audioIswc",
      "audioIsrc",
      "audioUpc"
    ]
  },
  "StemsIdDelete": {
    "Required": [
      "id"
    ],
    "Unrequired": []
  },
  "StemsIdGet": {
    "Required": [
      "id"
    ],
    "Unrequired": []
  },
  "StemsIdPut": {
    "Required": [
      "id",
      "audioTitle",
      "audioKey",
      "audioType",
      "audioReleaseDate",
      "audioText",
      "audioImage"
    ],
    "Unrequired": [
      "audioMixVersion",
      "audioSongId",
      "audioLabel",
      "audioArtist",
      "audioRemixer",
      "audioLyrics",
      "audioBpm",
      "audioIswc",
      "audioIsrc",
      "audioUpc"
    ]
  },
  "StemsListGet": {
    "Required": [],
    "Unrequired": [
      "limit",
      "title",
      "genre",
      "artist",
      "dateRangeFrom",
      "dateRangeTo"
    ]
  },
  "VideosCreatePost": {
    "Required": [
      "videoTitle",
      "videoGenre",
      "videoReleaseDate",
      "videoText",
      "videoImage",
      "videoKey"
    ],
    "Unrequired": [
      "videoMixVersion",
      "videoAlbum",
      "videoLabel",
      "videoArtist",
      "videoRemixer",
      "videoLyrics",
      "videoBpm",
      "videoIswc",
      "videoIsrc",
      "videoCatalog",
      "videoKobalt",
      "videoUpc"
    ]
  },
  "VideosIdDelete": {
    "Required": [
      "id"
    ],
    "Unrequired": []
  },
  "VideosIdGet": {
    "Required": [
      "id"
    ],
    "Unrequired": []
  },
  "VideosIdPut": {
    "Required": [
      "id"
    ],
    "Unrequired": [
      "videoTitle",
      "videoGenre",
      "videoReleaseDate",
      "videoText",
      "videoImage",
      "videoKey",
      "videoMixVersion",
      "videoAlbum",
      "videoLabel",
      "videoArtist",
      "videoRemixer",
      "videoLyrics",
      "videoBpm",
      "videoIswc",
      "videoIsrc",
      "videoCatalog",
      "videoKobalt",
      "videoUpc"
    ]
  },
  "VideosListGet": {
    "Required": [],
    "Unrequired": [
      "limit",
      "title",
      "genre",
      "artist",
      "dateRangeFrom",
      "dateRangeTo"
    ]
  },
  "UserIdDelete": {
    "Required": [
      "id"
    ],
    "Unrequired": []
  },
  "UserIdGet": {
    "Required": [
      "id"
    ],
    "Unrequired": []
  },
  "UserIdPut": {
    "Required": [
      "id"
    ],
    "Unrequired": [
      "email"
    ]
  },
  "UserLoginPost": {
    "Required": [
      "userName",
      "password"
    ],
    "Unrequired": []
  },
  "UserPost": {
    "Required": [
      "userEmail",
      "password",
      "userName"
    ],
    "Unrequired": []
  }
}